Workbook

Sheet asesores_ficticio
A1: asesor_id | B1: nombre_generico | C1: ciudad_base | D1: departamento | E1: latitud_base | F1: longitud_base | G1: capacidad_maxima_clientes
A2: ASE_001 | B2: Asesor_001 | C2: Medellín | D2: Antioquia | E2: 6.252566 | F2: -75.609699 | G2: 35
A3: ASE_002 | B3: Asesor_002 | C3: Bello | D3: Antioquia | E3: 6.321994 | F3: -75.579628 | G3: 25
A4: ASE_003 | B4: Asesor_003 | C4: Itagüí | D4: Antioquia | E4: 6.182502 | F4: -75.588669 | G4: 25
A5: ASE_004 | B5: Asesor_004 | C5: Rionegro | D5: Antioquia | E5: 6.16023 | F5: -75.402693 | G5: 25
A6: ASE_005 | B6: Asesor_005 | C6: Bogotá | D6: Cundinamarca | E6: 4.694118 | F6: -74.071779 | G6: 25
A7: ASE_006 | B7: Asesor_006 | C7: Soacha | D7: Cundinamarca | E7: 4.582975 | F7: -74.203639 | G7: 40
A8: ASE_007 | B8: Asesor_007 | C8: Cali | D8: Valle del Cauca | E8: 3.434826 | F8: -76.526644 | G8: 25
A9: ASE_008 | B9: Asesor_008 | C9: Barranquilla | D9: AtlÃ¡ntico | E9: 10.979428 | F9: -74.81682 | G9: 40
A10: ASE_009 | B10: Asesor_009 | C10: Bucaramanga | D10: Santander | E10: 7.109715 | F10: -73.143371 | G10: 35
A11: ASE_010 | B11: Asesor_010 | C11: Pereira | D11: Risaralda | E11: 4.790433 | F11: -75.701804 | G11: 35

Sheet clientes_ficticio
A1: cliente_id | B1: ciudad | C1: departamento | D1: latitud | E1: longitud | F1: fecha_desembolso | G1: producto_credito | H1: monto_desembolsado | I1: saldo_cartera | J1: dias_mora | K1: sector_economico | L1: ingresos_mensuales_estimados | M1: canal_adquisicion | N1: asesor_id_actual | O1: sexo | P1: edad | Q1: oferta_comercial | R1: tamano_negocio | S1: saldo_mora_30 | T1: tasa_mora_ciudad | U1: Ciudad_asesor | V1: MISMO_CIUDAD
A2: CLI_0001 | B2: Soacha | C2: Cundinamarca | D2: 4595896 | E2: -74167459 | F2: 45179 | G2: Crédito Rotativo | H2: 4000000 | I2: 1962045 | J2: 0 | K2: Alimentos | L2: 2000000 | M2: Visita en zona | N2: ASE_002 | O2: Masculino | P2: 47 | Q2: Ampliación de cupo | R2: Pequeña empresa | S2: =IF(Tabla1[[#This Row],[dias_mora]]>30,Tabla1[[#This Row],[saldo_cartera]],0) -> 0 | T2: =Tabla1[[#This Row],[saldo_mora_30]]/Tabla1[[#This Row],[saldo_cartera]] -> 0 | U2: =VLOOKUP(N2,asesores_ficticio!$A:$C,3,FALSE) -> Bello | V2: =IF(B2=U2,"SI","NO") -> NO | W2: {=SUMPRODUCT(--ISERROR(U2:U321))} -> 0 | X2: =COUNTBLANK(V2:V321) -> 0 | Y2: =COUNTIF(V2:V321,"SI") -> 23 | Z2: =COUNTIF(V2:V321,"SI") -> 23
A3: CLI_0002 | B3: Medellín | C3: Antioquia | D3: 6270002 | E3: -75537509 | F3: 45890 | G3: Crédito Rotativo | H3: 500000 | I3: 413510 | J3: 45 | K3: Servicios | L3: 2000000 | M3: Feria empresarial | N3: ASE_006 | O3: Femenino | P3: 45 | Q3: Reestructuración de deuda | R3: Pequeña empresa | S3: =IF(Tabla1[[#This Row],[dias_mora]]>30,Tabla1[[#This Row],[saldo_cartera]],0) -> 413510 | T3: =Tabla1[[#This Row],[saldo_mora_30]]/Tabla1[[#This Row],[saldo_cartera]] -> 1 | U3: =VLOOKUP(N3,asesores_ficticio!$A:$C,3,FALSE) -> Soacha | V3: =IF(B3=U3,"SI","NO") -> NO
A4: CLI_0003 | B4: Rionegro | C4: Antioquia | D4: 6182028 | E4: -75342309 | F4: 45366 | G4: Línea Emprendimiento | H4: 4000000 | I4: 2603320 | J4: 5 | K4: Manufactura | L4: 1300000 | M4: Aliado comercial | N4: ASE_004 | O4: Masculino | P4: 42 | Q4: Plan de alivio de pagos | R4: Microempresa | S4: =IF(Tabla1[[#This Row],[dias_mora]]>30,Tabla1[[#This Row],[saldo_cartera]],0) -> 0 | T4: =Tabla1[[#This Row],[saldo_mora_30]]/Tabla1[[#This Row],[saldo_cartera]] -> 0 | U4: =VLOOKUP(N4,asesores_ficticio!$A:$C,3,FALSE) -> Rionegro | V4: =IF(B4=U4,"SI","NO") -> SI | X4: =COUNTA(V2:V321) -> 320
A5: CLI_0004 | B5: Soacha | C5: Cundinamarca | D5: 4634156 | E5: -7417244 | F5: 45695 | G5: Crédito Rotativo | H5: 800000 | I5: 638826 | J5: 30 | K5: Servicios | L5: 2000000 | M5: Digital | N5: ASE_007 | O5: Femenino | P5: 30 | Q5: Reestructuración de deuda | R5: Pequeña empresa | S5: =IF(Tabla1[[#This Row],[dias_mora]]>30,Tabla1[[#This Row],[saldo_cartera]],0) -> 0 | T5: =Tabla1[[#This Row],[saldo_mora_30]]/Tabla1[[#This Row],[saldo_cartera]] -> 0 | U5: =VLOOKUP(N5,asesores_ficticio!$A:$C,3,FALSE) -> Cali | V5: =IF(B5=U5,"SI","NO") -> NO
A6: CLI_0005 | B6: Barranquilla | C6: Atlántico | D6: 10906759 | E6: -74854059 | F6: 46308 | G6: Crédito Rotativo | H6: 4000000 | I6: 2308652 | J6: 0 | K6: Servicios | L6: 2800000 | M6: Visita en zona | N6: ASE_009 | O6: Femenino | P6: 32 | Q6: Educación financiera + seguro | R6: Pequeña empresa | S6: =IF(Tabla1[[#This Row],[dias_mora]]>30,Tabla1[[#This Row],[saldo_cartera]],0) -> 0 | T6: =Tabla1[[#This Row],[saldo_mora_30]]/Tabla1[[#This Row],[saldo_cartera]] -> 0 | U6: =VLOOKUP(N6,asesores_ficticio!$A:$C,3,FALSE) -> Bucaramanga | V6: =IF(B6=U6,"SI","NO") -> NO
A7: CLI_0006 | B7: Barranquilla | C7: Atlántico | D7: 10898446 | E7: -74868861 | F7: 46298 | G7: Línea Emprendimiento | H7: 500000 | I7: 114958 | J7: 0 | K7: Agroindustria | L7: 3500000 | M7: Aliado comercial | N7: ASE_008 | O7: Masculino | P7: 29 | Q7: Ampliación de cupo | R7: Mediana empresa | S7: =IF(Tabla1[[#This Row],[dias_mora]]>30,Tabla1[[#This Row],[saldo_cartera]],0) -> 0 | T7: =Tabla1[[#This Row],[saldo_mora_30]]/Tabla1[[#This Row],[saldo_cartera]] -> 0 | U7: =VLOOKUP(N7,asesores_ficticio!$A:$C,3,FALSE) -> Barranquilla | V7: =IF(B7=U7,"SI","NO") -> SI
A8: CLI_0007 | B8: Bucaramanga | C8: Santander | D8: 7079526 | E8: -73114184 | F8: 45972 | G8: Microcrédito Individual | H8: 500000 | I8: 339120 | J8: 0 | K8: Manufactura | L8: 2800000 | M8: Digital | N8: ASE_003 | O8: Femenino | P8: 56 | Q8: Educación financiera + seguro | R8: Pequeña empresa | S8: =IF(Tabla1[[#This Row],[dias_mora]]>30,Tabla1[[#This Row],[saldo_cartera]],0) -> 0 | T8: =Tabla1[[#This Row],[saldo_mora_30]]/Tabla1[[#This Row],[saldo_cartera]] -> 0 | U8: =VLOOKUP(N8,asesores_ficticio!$A:$C,3,FALSE) -> Itagüí | V8: =IF(B8=U8,"SI","NO") -> NO
A9: CLI_0008 | B9: Barranquilla | C9: Atlántico | D9: 10884419 | E9: -74760865 | F9: 45240 | G9: Crédito Grupal Solidario | H9: 4000000 | I9: 1295523 | J9: 0 | K9: Servicios | L9: 1300000 | M9: Feria empresarial | N9: ASE_003 | O9: Femenino | P9: 57 | Q9: Ampliación de cupo | R9: Microempresa | S9: =IF(Tabla1[[#This Row],[dias_mora]]>30,Tabla1[[#This Row],[saldo_cartera]],0) -> 0 | T9: =Tabla1[[#This Row],[saldo_mora_30]]/Tabla1[[#This Row],[saldo_cartera]] -> 0 | U9: =VLOOKUP(N9,asesores_ficticio!$A:$C,3,FALSE) -> Itagüí | V9: =IF(B9=U9,"SI","NO") -> NO
A10: CLI_0009 | B10: Bucaramanga | C10: Santander | D10: 719186 | E10: -73055111 | F10: 45785 | G10: Microcrédito Individual | H10: 500000 | I10: 304551 | J10: 0 | K10: Servicios | L10: 900000 | M10: Aliado comercial | N10: ASE_002 | O10: Masculino | P10: 63 | Q10: Educación financiera + seguro | R10: Microempresa | S10: =IF(Tabla1[[#This Row],[dias_mora]]>30,Tabla1[[#This Row],[saldo_cartera]],0) -> 0 | T10: =Tabla1[[#This Row],[saldo_mora_30]]/Tabla1[[#This Row],[saldo_cartera]] -> 0 | U10: =VLOOKUP(N10,asesores_ficticio!$A:$C,3,FALSE) -> Bello | V10: =IF(B10=U10,"SI","NO") -> NO
A11: CLI_0010 | B11: Bello | C11: Antioquia | D11: 6374405 | E11: -75507436 | F11: 46271 | G11: Crédito Rotativo | H11: 6000000 | I11: 3316801 | J11: 0 | K11: Alimentos | L11: 3500000 | M11: Aliado comercial | N11: ASE_007 | O11: Masculino | P11: 36 | Q11: Educación financiera + seguro | R11: Mediana empresa | S11: =IF(Tabla1[[#This Row],[dias_mora]]>30,Tabla1[[#This Row],[saldo_cartera]],0) -> 0 | T11: =Tabla1[[#This Row],[saldo_mora_30]]/Tabla1[[#This Row],[saldo_cartera]] -> 0 | U11: =VLOOKUP(N11,asesores_ficticio!$A:$C,3,FALSE) -> Cali | V11: =IF(B11=U11,"SI","NO") -> NO
A12: CLI_0011 | B12: Rionegro | C12: Antioquia | D12: 6223426 | E12: -75333758 | F12: 45886 | G12: Línea Emprendimiento | H12: 4000000 | I12: 1083914 | J12: 0 | K12: Comercio | L12: 3500000 | M12: Visita en zona | N12: ASE_004 | O12: Masculino | P12: 61 | Q12: Ampliación de cupo | R12: Mediana empresa | S12: =IF(Tabla1[[#This Row],[dias_mora]]>30,Tabla1[[#This Row],[saldo_cartera]],0) -> 0 | T12: =Tabla1[[#This Row],[saldo_mora_30]]/Tabla1[[#This Row],[saldo_cartera]] -> 0 | U12: =VLOOKUP(N12,asesores_ficticio!$A:$C,3,FALSE) -> Rionegro | V12: =IF(B12=U12,"SI","NO") -> SI
A13: CLI_0012 | B13: Bello | C13: Antioquia | D13: 6311394 | E13: -75543871 | F13: 45019 | G13: Microcrédito Individual | H13: 800000 | I13: 480139 | J13: 0 | K13: Manufactura | L13: 3500000 | M13: Referido | N13: ASE_009 | O13: Femenino | P13: 48 | Q13: Educación financiera + seguro | R13: Mediana empresa | S13: =IF(Tabla1[[#This Row],[dias_mora]]>30,Tabla1[[#This Row],[saldo_cartera]],0) -> 0 | T13: =Tabla1[[#This Row],[saldo_mora_30]]/Tabla1[[#This Row],[saldo_cartera]] -> 0 | U13: =VLOOKUP(N13,asesores_ficticio!$A:$C,3,FALSE) -> Bucaramanga | V13: =IF(B13=U13,"SI","NO") -> NO
A14: CLI_0013 | B14: Rionegro | C14: Antioquia | D14: 6119356 | E14: -75376934 | F14: 46138 | G14: Línea Emprendimiento | H14: 2500000 | I14: 531163 | J14: 60 | K14: Agroindustria | L14: 2800000 | M14: Visita en zona | N14: ASE_002 | O14: Masculino | P14: 42 | Q14: Reestructuración de deuda | R14: Pequeña empresa | S14: =IF(Tabla1[[#This Row],[dias_mora]]>30,Tabla1[[#This Row],[saldo_cartera]],0) -> 531163 | T14: =Tabla1[[#This Row],[saldo_mora_30]]/Tabla1[[#This Row],[saldo_cartera]] -> 1 | U14: =VLOOKUP(N14,asesores_ficticio!$A:$C,3,FALSE) -> Bello | V14: =IF(B14=U14,"SI","NO") -> NO
A15: CLI_0014 | B15: Bello | C15: Antioquia | D15: 6362737 | E15: -75581312 | F15: 44939 | G15: Crédito Rotativo | H15: 1800000 | I15: 894548 | J15: 15 | K15: Comercio | L15: 3500000 | M15: Visita en zona | N15: ASE_004 | O15: Masculino | P15: 60 | Q15: Plan de alivio de pagos | R15: Mediana empresa | S15: =IF(Tabla1[[#This Row],[dias_mora]]>30,Tabla1[[#This Row],[saldo_cartera]],0) -> 0 | T15: =Tabla1[[#This Row],[saldo_mora_30]]/Tabla1[[#This Row],[saldo_cartera]] -> 0 | U15: =VLOOKUP(N15,asesores_ficticio!$A:$C,3,FALSE) -> Rionegro | V15: =IF(B15=U15,"SI","NO") -> NO
A16: CLI_0015 | B16: Rionegro | C16: Antioquia | D16: 6160606 | E16: -75432171 | F16: 46269 | G16: Microcrédito Individual | H16: 800000 | I16: 269411 | J16: 0 | K16: Alimentos | L16: 900000 | M16: Referido | N16: ASE_002 | O16: Femenino | P16: 60 | Q16: Ampliación de cupo | R16: Microempresa | S16: =IF(Tabla1[[#This Row],[dias_mora]]>30,Tabla1[[#This Row],[saldo_cartera]],0) -> 0 | T16: =Tabla1[[#This Row],[saldo_mora_30]]/Tabla1[[#This Row],[saldo_cartera]] -> 0 | U16: =VLOOKUP(N16,asesores_ficticio!$A:$C,3,FALSE) -> Bello | V16: =IF(B16=U16,"SI","NO") -> NO
... A321: CLI_0320 | B321: Barranquilla | C321: Atlántico | D321: 10908912 | E321: -74841221 | F321: 45966 | G321: Crédito Rotativo | H321: 4000000 | I321: 1729375 | J321: 30 | K321: Manufactura | L321: 2800000 | M321: Referido | N321: ASE_009 | O321: Masculino | P321: 48 | Q321: Reestructuración de deuda | R321: Pequeña empresa | S321: =IF(Tabla1[[#This Row],[dias_mora]]>30,Tabla1[[#This Row],[saldo_cartera]],0) -> 0 | T321: =Tabla1[[#This Row],[saldo_mora_30]]/Tabla1[[#This Row],[saldo_cartera]] -> 0 | U321: =VLOOKUP(N321,asesores_ficticio!$A:$C,3,FALSE) -> Bucaramanga | V321: =IF(B321=U321,"SI","NO") -> NO

Sheet punto 1 y 2
A1: punto 1 | B1: 1. Saldo total de cartera y cartera en mora (>30 días) por ciudad.
A3: Etiquetas de fila | B3: Suma de saldo_cartera | C3: Suma de saldo_mora_30 | D3: Suma de saldo_mora_30_2 | E3: % CARTERA EN MORA
A4: Cali | B4: 57750191 | C4: 13240914 | D4: 0.29038067 | E4: =C4/B4 -> 0.22927914
A5: Bello | B5: 54404332 | C5: 6833546 | D5: 0.1498635 | E5: =C5/B5 -> 0.12560665
A6: Itagüí | B6: 34910306 | C6: 6378456 | D6: 0.13988312 | E6: =C6/B6 -> 0.18270983
A7: Bogotá | B7: 45723154 | C7: 4348951 | D7: 0.095374935 | E7: =C7/B7 -> 0.095114851
A8: Bucaramanga | B8: 46797287 | C8: 3697629 | D8: 0.081091078 | E8: =C8/B8 -> 0.079013747
A9: Soacha | B9: 41401323 | C9: 2727658 | D9: 0.05981907 | E9: =C9/B9 -> 0.065883354
A10: Medellín | B10: 25978256 | C10: 2545962 | D10: 0.055834375 | E10: =C10/B10 -> 0.098003577
A11: Barranquilla | B11: 34417841 | C11: 2105511 | D11: 0.046175037 | E11: =C11/B11 -> 0.061174988
A12: Rionegro | B12: 39735794 | C12: 1977941 | D12: 0.043377355 | E12: =C12/B12 -> 0.049777312
A13: Pereira | B13: 31534234 | C13: 1741901 | D13: 0.038200866 | E13: =C13/B13 -> 0.055238412
A14: Total general | B14: 412652718 | C14: 45598469 | D14: 1 | E14: =C14/B14 -> 0.11050083
A33: PUNTO 2 | B33: 2. Top 5 asesores con mayor saldo de cartera en mora (>30 días).
A35: Etiquetas de fila | B35: Suma de saldo_mora_30 | C35: Suma de saldo_mora_30_2
A36: ASE_004 | B36: 11436467 | C36: 0.25080814
A37: ASE_005 | B37: 10806007 | C37: 0.23698179
A38: ASE_008 | B38: 7913618 | C38: 0.17355008
A39: ASE_001 | B39: 5566259 | C39: 0.12207118
A40: ASE_009 | B40: 2744784 | C40: 0.060194653
A41: ASE_002 | B41: 2320328 | C41: 0.050886094
A42: ASE_006 | B42: 1630097 | C42: 0.035748941
A43: ASE_010 | B43: 1573302 | C43: 0.034503395
A44: ASE_007 | B44: 828791 | C44: 0.018175851
A45: ASE_003 | B45: 778816 | C45: 0.017079872
A46: Total general | B46: 45598469 | C46: 1
A57: GRAFICO DENDROGRAMAS !!!!

Sheet punto 3-PUNTO 4
A1: 3. Distribución de clientes y saldo de cartera por producto de crédito y sector económico.
A3: Suma de saldo_cartera | B3: Etiquetas de columna
A4: Etiquetas de fila | B4: Agroindustria | C4: Alimentos | D4: Comercio | E4: Manufactura | F4: Servicios | G4: Total general
A5: Línea Emprendimiento | B5: 20759418 | C5: 19013820 | D5: 23420482 | E5: 23566452 | F5: 23855643 | G5: 110615815
A6: Crédito Rotativo | B6: 20617865 | C6: 25997527 | D6: 26595605 | E6: 15536576 | F6: 21166954 | G6: 109914527
A7: Crédito Grupal Solidario | B7: 17637042 | C7: 20699823 | D7: 15621491 | E7: 24609204 | F7: 26865619 | G7: 105433179
A8: Microcrédito Individual | B8: 18993716 | C8: 12581916 | D8: 20162009 | E8: 20454972 | F8: 14496584 | G8: 86689197
A9: Total general | B9: 78008041 | C9: 78293086 | D9: 85799587 | E9: 84167204 | F9: 86384800 | G9: 412652718
A22: Etiquetas de fila | B22: Suma de saldo_cartera | C22: Suma de saldo_mora_30 | D22: MORA POR PRODUCTO
A23: Microcrédito Individual | B23: 86689197 | C23: 19252748 | D23: =C23/B23 -> 0.22208936
A24: Línea Emprendimiento | B24: 110615815 | C24: 13595297 | D24: =C24/B24 -> 0.12290554
A25: Crédito Grupal Solidario | B25: 105433179 | C25: 8475143 | D25: =C25/B25 -> 0.080384022
A26: Crédito Rotativo | B26: 109914527 | C26: 4275281 | D26: =C26/B26 -> 0.038896414
A27: Total general | B27: 412652718 | C27: 45598469 | D27: =C27/B27 -> 0.11050083
A43: grafica anexos
A47: PUNTO 4

Sheet ANALISIS DE ESCENARIOS_CALI
A1: ANÁLISIS DE ESCENARIOS - CUPO ADICIONAL PARA CALI (Bloque B3 - Extra)
A2: Objetivo: estimar la cartera en riesgo si se asigna un cupo adicional de $1,000 millones a clientes de Cali, bajo 3 escenarios que representan distintas políticas de originación (a quién se le presta), usando tasas de mora reales observadas en los segmentos de clientes definidos en B2. - Pesimista: se presta a TODOS los clientes de Cali por igual (tasa histórica de Cali). - Medio: se excluye únicamente al segmento "Riesgo alto" (de B2). - Optimista: se presta solo a los segmentos "Bajo riesgo" y "Base estándar" (de B2). Las tasas de mora usadas provienen de datos observados (Excel B1 y Python B2), no de supuestos arbitrarios.
A12: ¿debería prestar más ahí, y bajo qué condiciones?"
A16: tasa de mora que se observo enlos clientes de cali punto 1
A17: Escenario | B17: Tasa de mora esperada para cali | C17: Cupo adicional | D17: Cartera en riesgo
A18: Pesimista | B18: 0.2293 | C18: 1000000000 | D18: =C18*B21 -> 229300000
A19: medio | B19: 0.1933 | C19: 1000000000
A20: optimista | B20: 0 | C20: 1000000000
B21: 0.2293
B22: 0.1933

Sheet Resumen del escenario 2
B2: Resumen del escenario
D3: Valores actuales: | E3: pesimista | F3: medio | G3: optimista
E4: Creado por Andres Cerquera el 05/09/2026 | F4: Creado por Andres Cerquera el 05/09/2026 | G4: Creado por Andres Cerquera el 05/09/2026
B5: Celdas cambiantes:
C6: $B$21 | D6: 0.2293 | E6: 0.2293 | F6: 0.1933 | G6: 0
B7: Celdas de resultado:
C8: $D$18 | D8: 229300000 | E8: 229300000 | F8: 193300000 | G8: 0 | H8: dinero que probablemente entrara en mora bsado en el comportamiento historico observado
B9: Notas: La columna de valores actuales representa los valores de las celdas cambiantes
B10: en el momento en que se creó el Informe resumen de escenario. Las celdas cambiantes de
B11: cada escenario se muestran en gris.
B13: RECOMENDACION:Enfocar el nuevo cupo en los clusters "Bajo riesgo" y "Base estándar" (los definidos en B2), y evitar por completo al cluster "Riesgo alto". no se recomienda frenar el crecimiento en Cali, pero sí canalizarlo selectivamente hacia los clientes de mejor comportamiento histórico, en vez de repartir el cupo nuevo de forma pareja entre todos.
